pavise/__init__.py
pavise/exceptions.py
pavise/pandas.py
pavise/polars.py
pavise/types.py
pavise/validators.py
pavise/_pandas/__init__.py
pavise/_pandas/validation.py
pavise/_pandas/validator_impl.py
pavise/_polars/__init__.py
pavise/_polars/validation.py
pavise/_polars/validator_impl.py
pavise-0.1.3.dist-info/METADATA
pavise-0.1.3.dist-info/WHEEL
pavise-0.1.3.dist-info/RECORD
