Metadata-Version: 2.4
Name: pavise
Version: 0.1.3
Summary: DataFrame validation library using Python Protocol for structural subtyping
Author: kitagry
License: MIT
Requires-Python: >=3.9
Requires-Dist: typing-extensions>=4.0.0
Provides-Extra: all
Requires-Dist: pandas>=1.3.0; extra == 'all'
Requires-Dist: polars>=0.15.0; extra == 'all'
Provides-Extra: dev
Requires-Dist: pandas>=1.3.0; extra == 'dev'
Requires-Dist: polars>=0.15.0; extra == 'dev'
Requires-Dist: pyrefly>=0.1.0; extra == 'dev'
Requires-Dist: pytest-cov>=4.0.0; extra == 'dev'
Requires-Dist: pytest>=7.0.0; extra == 'dev'
Requires-Dist: ruff>=0.1.0; extra == 'dev'
Requires-Dist: sphinx-rtd-theme>=1.0.0; extra == 'dev'
Requires-Dist: sphinx>=5.0.0; extra == 'dev'
Requires-Dist: tox>=4.0.0; extra == 'dev'
Provides-Extra: docs
Requires-Dist: sphinx-rtd-theme>=1.0.0; extra == 'docs'
Requires-Dist: sphinx>=5.0.0; extra == 'docs'
Provides-Extra: pandas
Requires-Dist: pandas>=1.3.0; extra == 'pandas'
Provides-Extra: polars
Requires-Dist: polars>=0.15.0; extra == 'polars'
